dictfier/__init__.py
dictfier/api.py
dictfier/exceptions.py
dictfier/factory.py
dictfier/filter.py
dictfier-1.5.1.dist-info/LICENSE
dictfier-1.5.1.dist-info/METADATA
dictfier-1.5.1.dist-info/WHEEL
dictfier-1.5.1.dist-info/top_level.txt
dictfier-1.5.1.dist-info/RECORD
